<?xml version="1.0" encoding="UTF-8" standalone="no"?>
<data>
    <classRoom id="0">
        <ClassNumber>54</ClassNumber>
        <DeskNumbers>5</DeskNumbers>
        <Desks id="0">
            <LeftSeat>null</LeftSeat>
            <RightSeat>null</RightSeat>
        </Desks>
        <Desks id="1">
            <LeftSeat>null</LeftSeat>
            <RightSeat>null</RightSeat>
        </Desks>
        <Desks id="2">
            <LeftSeat>null</LeftSeat>
            <RightSeat>null</RightSeat>
        </Desks>
        <Desks id="3">
            <LeftSeat>null</LeftSeat>
            <RightSeat>null</RightSeat>
        </Desks>
        <Desks id="4">
            <LeftSeat>null</LeftSeat>
            <RightSeat>null</RightSeat>
        </Desks>
    </classRoom>
</data>
